pyconsole_util/__init__.py
pyconsole_util/util.py
pyconsole_util-1.0.1.dist-info/LICENSE.txt
pyconsole_util-1.0.1.dist-info/METADATA
pyconsole_util-1.0.1.dist-info/WHEEL
pyconsole_util-1.0.1.dist-info/top_level.txt
pyconsole_util-1.0.1.dist-info/RECORD
