Metadata-Version: 2.1
Name: pyconsole-util
Version: 1.0.1
Summary: A set of functions that print to the console in different formats for debugging, exploring, or printing nicely
Home-page: https://github.com/Hugernot/pyconsole-util
Author: Gatlen Culp
Author-email: gatlenculp@gmail.com
License: GPLv3
Keywords: console printing colors formatting format debug info explorer
Platform: UNKNOWN
Classifier: Development Status :: 2 - Pre-Alpha
Classifier: Environment :: Console
Classifier: Intended Audience :: Developers
Classifier: Programming Language :: Python :: 3.7
Classifier: License :: OSI Approved :: GNU General Public License v3 (GPLv3)
Classifier: Operating System :: OS Independent
Classifier: Topic :: Software Development :: Debuggers
